example/maimai.py
example/nostalgia.py
example/pchord.py
example/popn.py
otoge/__init__.py
otoge/enum.py
otoge/exceptions.py
otoge/konami.py
otoge/konami_captcha.py
otoge/logger.py
otoge/maimai.py
otoge/nostalgia.py
otoge/paseli.py
otoge/polarischord.py
otoge/popn.py
otoge/utils.py
otoge.py-0.2.1.dist-info/LICENSE
otoge.py-0.2.1.dist-info/METADATA
otoge.py-0.2.1.dist-info/WHEEL
otoge.py-0.2.1.dist-info/top_level.txt
otoge.py-0.2.1.dist-info/RECORD
