Metadata-Version: 2.2
Name: otoge.py
Version: 0.2.1
Summary: You can get and change the play history of GEKICHUMAI (CHUNITHM, ONGEKI, maimai), BEMANI (pop'n music, beatmania, SOUND VORTEX) and many more.
Author-email: nennneko5787 <h4369@nennneko5787.net>
Project-URL: Homepage, https://github.com/nennneko5787/otoge.py
Project-URL: Issues, https://github.com/nennneko5787/otoge.py/issues
Classifier: Programming Language :: Python :: 3
Classifier: License :: OSI Approved :: GNU Affero General Public License v3
Classifier: Operating System :: OS Independent
Classifier: Natural Language :: Japanese
Requires-Python: >=3.9
License-File: LICENSE
Requires-Dist: httpx
Requires-Dist: beautifulsoup4
Requires-Dist: selenium
Requires-Dist: python-dateutil
Requires-Dist: tzdata
